ppyoloe/__init__.py
ppyoloe/onnx_predict.py
ppyoloe/predict.py
ppyoloe/trainer.py
ppyoloe/data_utils/__init__.py
ppyoloe/data_utils/batch_operators.py
ppyoloe/data_utils/dataset.py
ppyoloe/data_utils/operators.py
ppyoloe/data_utils/reader.py
ppyoloe/data_utils/utils.py
ppyoloe/metrics/__init__.py
ppyoloe/metrics/coco_utils.py
ppyoloe/metrics/metrics.py
ppyoloe/model/__init__.py
ppyoloe/model/atss_assigner.py
ppyoloe/model/atss_utils.py
ppyoloe/model/bbox_utils.py
ppyoloe/model/cspresnet.py
ppyoloe/model/custom_pan.py
ppyoloe/model/initializer.py
ppyoloe/model/iou_loss.py
ppyoloe/model/layers.py
ppyoloe/model/meta_arch.py
ppyoloe/model/ppyoloe_head.py
ppyoloe/model/task_aligned_assigner.py
ppyoloe/model/utils.py
ppyoloe/model/yolo.py
ppyoloe/utils/__init__.py
ppyoloe/utils/logger.py
ppyoloe/utils/lr.py
ppyoloe/utils/utils.py
ppyoloe-0.0.1.dist-info/LICENSE
ppyoloe-0.0.1.dist-info/METADATA
ppyoloe-0.0.1.dist-info/WHEEL
ppyoloe-0.0.1.dist-info/top_level.txt
ppyoloe-0.0.1.dist-info/RECORD
