Metadata-Version: 2.1
Name: ppyoloe
Version: 0.0.1
Summary: PPYOLOE Object Detection toolkit on PaddlePaddle
Home-page: https://github.com/yeyupiaoling/PP-YOLOE
Author: yeyupiaoling
License: Apache License 2.0
Download-URL: https://github.com/yeyupiaoling/PP-YOLOE.git
Keywords: PPYOLOE,paddle,Detection
Platform: UNKNOWN
Classifier: Intended Audience :: Developers
Classifier: License :: OSI Approved :: Apache Software License
Classifier: Operating System :: OS Independent
Classifier: Natural Language :: Chinese (Simplified)
Classifier: Programming Language :: Python :: 3
Classifier: Programming Language :: Python :: 3.5
Classifier: Programming Language :: Python :: 3.6
Classifier: Programming Language :: Python :: 3.7
Classifier: Programming Language :: Python :: 3.8
Classifier: Programming Language :: Python :: 3.9
Classifier: Topic :: Utilities
License-File: LICENSE
Requires-Dist: numpy (>=1.21.2)
Requires-Dist: requests (>=2.25.1)
Requires-Dist: tqdm (>=4.59.0)
Requires-Dist: termcolor (>=1.1.0)
Requires-Dist: opencv-python (~=4.5.5.64)
Requires-Dist: pillow (>=8.3.2)
Requires-Dist: pycocotools (>=2.0)
Requires-Dist: visualdl (>=2.2.0)
Requires-Dist: paddlelite (>=2.11)
Requires-Dist: paddle2onnx (>=0.9.8)
